harsh/__init__.py
harsh/main.py
harshchitaliya/__init__.py
harshchitaliya/main.py
harshchitaliya-0.1.1.dist-info/METADATA
harshchitaliya-0.1.1.dist-info/WHEEL
harshchitaliya-0.1.1.dist-info/top_level.txt
harshchitaliya-0.1.1.dist-info/RECORD
